wiremongo/__init__.py
wiremongo/tools.py
wiremongo-0.1.3.dist-info/METADATA
wiremongo-0.1.3.dist-info/WHEEL
wiremongo-0.1.3.dist-info/licenses/LICENSE
wiremongo-0.1.3.dist-info/RECORD
