Metadata-Version: 2.4
Name: wiremongo
Version: 0.1.3
Summary: A test library to mock MongoDB commands with AsyncMongoClient compatibility
License-File: LICENSE
Author: Christoph Spörk
Author-email: christoph.spoerk@gmail.com
Requires-Python: >=3.12,<4.0
Classifier: Programming Language :: Python :: 3
Classifier: Programming Language :: Python :: 3.12
Classifier: Programming Language :: Python :: 3.13
Classifier: Programming Language :: Python :: 3.14
Requires-Dist: pymongo (>=4.0.0,<5.0.0)
